codecov/__init__.py
codecov/badge.py
codecov/coverage.py
codecov/diff_grouper.py
codecov/github.py
codecov/github_client.py
codecov/groups.py
codecov/log.py
codecov/main.py
codecov/settings.py
codecov/template.py
codecov/template_files/comment.md.j2
codecov/template_files/macros.md.j2
codecov/template_files/pr.md.j2
codecov/template_files/project.md.j2
python_coverage_comment-2.1.dist-info/LICENSE
python_coverage_comment-2.1.dist-info/METADATA
python_coverage_comment-2.1.dist-info/WHEEL
python_coverage_comment-2.1.dist-info/entry_points.txt
python_coverage_comment-2.1.dist-info/top_level.txt
python_coverage_comment-2.1.dist-info/RECORD
