Metadata-Version: 2.1
Name: python-coverage-comment
Version: 2.1
Summary: Create a Coverage report comment on Github PR
Maintainer-email: Pradeep Tammali <pradeeptammaliwork@gmail.com>
License: MIT License
Project-URL: Homepage, https://github.com/PradeepTammali/python-coverage-comment
Project-URL: Issues, https://github.com/PradeepTammali/python-coverage-comment/issues
Classifier: Programming Language :: Python :: 3 :: Only
Classifier: Programming Language :: Python :: 3.0
Classifier: Programming Language :: Python :: 3.1
Classifier: Programming Language :: Python :: 3.2
Classifier: Programming Language :: Python :: 3.3
Classifier: Programming Language :: Python :: 3.4
Classifier: Programming Language :: Python :: 3.5
Classifier: Programming Language :: Python :: 3.6
Classifier: Programming Language :: Python :: 3.7
Classifier: Programming Language :: Python :: 3.8
Classifier: Programming Language :: Python :: 3.9
Classifier: Programming Language :: Python :: 3.10
Classifier: Programming Language :: Python :: 3.11
Requires-Python: >=3.0
License-File: LICENSE
Requires-Dist: httpx
Requires-Dist: jinja2
